LICENSE
pyopenfisheries/__init__.py
pyopenfisheries/pyopenfisheries.py
pyopenfisheries-0.1.2.dist-info/LICENSE
pyopenfisheries-0.1.2.dist-info/WHEEL
pyopenfisheries-0.1.2.dist-info/METADATA
pyopenfisheries-0.1.2.dist-info/RECORD
