Metadata-Version: 2.1
Name: pyopenfisheries
Version: 0.1.2
Summary:  PyOpenFisheries makes it even easier to access the OpenFisheries API in Python. A good usecase of this library is to gather data to plot in a Jupyter Notebook, or to collect data to run time-series analysis on.
Home-page: https://github.com/HenryKobin/PyOpenFisheries
License: Apache-2.0
Keywords: openfisheries,fish,fish_api,plotting
Author: Henry Kobin
Author-email: henry.kobin@gmail.com
Requires-Python: >=3.8,<4.0
Classifier: License :: OSI Approved :: Apache Software License
Classifier: Programming Language :: Python :: 3
Classifier: Programming Language :: Python :: 3.8
Classifier: Programming Language :: Python :: 3.9
Requires-Dist: requests (>=2.5,<3.0)
Project-URL: Repository, https://github.com/HenryKobin/PyOpenFisheries
